webex_handler/__init__.py
webex_handler/async_webex.py
webex_handler/webex.py
webex_handler-2.0.0.dist-info/LICENSE
webex_handler-2.0.0.dist-info/METADATA
webex_handler-2.0.0.dist-info/WHEEL
webex_handler-2.0.0.dist-info/top_level.txt
webex_handler-2.0.0.dist-info/RECORD
