Metadata-Version: 2.1
Name: webex-handler
Version: 2.0.0
Summary: A python logging handler that logs to Webex incoming webhooks
Home-page: https://github.com/xorrkaz/webex-log-handler
Author: Joe Clarke
Author-email: jclarke@cisco.com
License: MIT
Keywords: Elemental
Platform: UNKNOWN
Classifier: Intended Audience :: Developers
Classifier: License :: OSI Approved :: MIT License
Classifier: Programming Language :: Python :: 3.6
Requires-Python: >=3.6
Requires-Dist: requests
